cfman/.version
cfman/__classpath__.py
cfman/__init__.py
cfman/__main__.py
cfman/welcome.txt
cfman/core/__init__.py
cfman/core/cf.py
cfman/core/cf_application.py
cfman/core/cf_blue_green_checker.py
cfman/core/cf_endpoint.py
cfman/core/cf_manager.py
cfman/exception/__init__.py
cfman/exception/exceptions.py
hspylib_cfman-0.9.144.dist-info/METADATA
hspylib_cfman-0.9.144.dist-info/WHEEL
hspylib_cfman-0.9.144.dist-info/top_level.txt
hspylib_cfman-0.9.144.dist-info/RECORD
