Metadata-Version: 2.1
Name: hspylib-cfman
Version: 0.9.144
Summary: HsPyLib - CloudFoundry manager
Home-page: https://github.com/yorevs/hspylib
Author: Hugo Saporetti Junior
Author-email: yorevs@hotmail.com
License: MIT
Project-URL: GitHub, https://github.com/yorevs/hspylib
Project-URL: PyPi, https://pypi.org/project/hspylib-cfman/
Keywords: pivotal,pcf,cloudfoundry,manager,application
Platform: Darwin
Platform: Linux
Classifier: License :: OSI Approved :: MIT License
Classifier: Programming Language :: Python :: 3.10
Classifier: Operating System :: MacOS :: MacOS X
Classifier: Operating System :: POSIX :: Linux
Classifier: Operating System :: Unix
Classifier: Development Status :: 3 - Alpha
Classifier: Environment :: Console
Classifier: Natural Language :: English
Classifier: Topic :: Terminals
Classifier: Intended Audience :: Developers
Requires-Python: >=3.10
Requires-Dist: hspylib
Requires-Dist: hspylib-clitt
Requires-Dist: retry2 >=0.9.5
Requires-Dist: requests >=2.32.3
Requires-Dist: urllib3 >=2.2.2
